binary_gurdeep/__init__.py
binary_gurdeep/binary_ops.py
binary_gurdeep-0.1.0.dist-info/LICENSE
binary_gurdeep-0.1.0.dist-info/METADATA
binary_gurdeep-0.1.0.dist-info/WHEEL
binary_gurdeep-0.1.0.dist-info/top_level.txt
binary_gurdeep-0.1.0.dist-info/RECORD
