Metadata-Version: 2.1
Name: binary-gurdeep
Version: 0.1.0
Summary: A simple binary arithmetic library using 2's complement
Home-page: https://github.com/gurdeep/binary_gurdeep
Author: Gurdeep
Author-email: gurdeep@example.com
Classifier: Programming Language :: Python :: 3
Classifier: License :: OSI Approved :: MIT License
Classifier: Operating System :: OS Independent
Requires-Python: >=3.6
License-File: LICENSE
